detective_benno/__init__.py
detective_benno/cli.py
detective_benno/config.py
detective_benno/models.py
detective_benno/prompts.py
detective_benno/reviewer.py
detective_benno-0.1.0.dist-info/METADATA
detective_benno-0.1.0.dist-info/WHEEL
detective_benno-0.1.0.dist-info/entry_points.txt
detective_benno-0.1.0.dist-info/licenses/LICENSE
detective_benno-0.1.0.dist-info/licenses/NOTICE
detective_benno-0.1.0.dist-info/RECORD
