Metadata-Version: 2.4
Name: detective-benno
Version: 0.1.0
Summary: An intelligent code review detective powered by LLM - solving code mysteries, one PR at a time
Project-URL: Homepage, https://github.com/bimakw/detective-benno
Project-URL: Documentation, https://github.com/bimakw/detective-benno#readme
Project-URL: Repository, https://github.com/bimakw/detective-benno.git
Project-URL: Issues, https://github.com/bimakw/detective-benno/issues
Project-URL: Changelog, https://github.com/bimakw/detective-benno/blob/main/CHANGELOG.md
Author-email: Bima Kharisma Wicaksana <bimakw@users.noreply.github.com>
License-Expression: Apache-2.0
License-File: LICENSE
License-File: NOTICE
Keywords: ai,automation,code-review,detective,devtools,github,llm,openai,security
Classifier: Development Status :: 4 - Beta
Classifier: Environment :: Console
Classifier: Intended Audience :: Developers
Classifier: License :: OSI Approved :: Apache Software License
Classifier: Operating System :: OS Independent
Classifier: Programming Language :: Python :: 3
Classifier: Programming Language :: Python :: 3.10
Classifier: Programming Language :: Python :: 3.11
Classifier: Programming Language :: Python :: 3.12
Classifier: Topic :: Software Development :: Quality Assurance
Classifier: Topic :: Software Development :: Testing
Requires-Python: >=3.10
Requires-Dist: click>=8.0.0
Requires-Dist: gitpython>=3.1.0
Requires-Dist: httpx>=0.25.0
Requires-Dist: openai>=1.0.0
Requires-Dist: pydantic>=2.0.0
Requires-Dist: pygments>=2.15.0
Requires-Dist: pyyaml>=6.0
Requires-Dist: rich>=13.0.0
Provides-Extra: dev
Requires-Dist: mypy>=1.0.0; extra == 'dev'
Requires-Dist: pre-commit>=3.0.0; extra == 'dev'
Requires-Dist: pytest-asyncio>=0.21.0; extra == 'dev'
Requires-Dist: pytest-cov>=4.0.0; extra == 'dev'
Requires-Dist: pytest>=7.0.0; extra == 'dev'
Requires-Dist: ruff>=0.1.0; extra == 'dev'
Provides-Extra: github
Requires-Dist: pygithub>=2.0.0; extra == 'github'
